capvalidator/__init__.py
capvalidator/cli.py
capvalidator/validate.py
capvalidator/static/CAP-v1.2-schema.xsd
capvalidator-0.1.0.dev4.dist-info/LICENSE
capvalidator-0.1.0.dev4.dist-info/METADATA
capvalidator-0.1.0.dev4.dist-info/WHEEL
capvalidator-0.1.0.dev4.dist-info/top_level.txt
capvalidator-0.1.0.dev4.dist-info/RECORD
