Metadata-Version: 2.1
Name: capvalidator
Version: 0.1.0.dev4
Summary: Python module to validate a CAP message against the OASIS CAP 1.2 schema and verify the XML signature.
Author: Rory Burke
Maintainer-email: Rory Burke <rburke@wmo.int>
License: Apache License
Keywords: WIS2.0,CAP,XML,validator
Requires-Python: >=3.8
License-File: LICENSE
Requires-Dist: click>=8.1.7
Requires-Dist: lxml>=5.2.2
Requires-Dist: cryptography>=42.0.8
Requires-Dist: signxml>=3.2.2
